{
  "stream_file_frequency": {
    "monthly": {
      "streams": [
        "ap4",
        "ap5",
        "apm",
        "apu",
        "onm",
        "inm",
        "ind",
        "ond"
      ],
      "files_per_year": 12
    },
    "1 day": {
      "streams": [
        "apa"
      ],
      "files_per_year": 360
    }
  },
  "cycle_length": {
    "apa": "P1Y"
  },
  "memory": {
    "apa": "32G"
  },
  "temp_space": {
    "apa": 131072
  },
  "sizing_info": {
    "day": {
      "default": 5
    }
  },
  "subdaily_streams": [
    "apa"
  ],
  "grid_info": {
    "atmos": {
      "atmos_timestep": null,
      "model_info": "",
      "nominal_resolution": "",
      "longitude": null,
      "latitude": null,
      "v_latitude": null,
      "levels": null,
      "ancil_filenames": [
        "qrparm.landfrac.pp", "qrparm.soil.pp"
      ],
      "hybrid_heights_files": [
        "atmosphere_theta_levels_85.txt",
        "atmosphere_rho_levels_86.txt"
      ]
    },
    "ocean": {
      "model_info": "",
      "nominal_resolution": "",
      "longitude": null,
      "latitude": null,
      "levels": null,
      "replacement_coordinates_file": null,
      "ancil_filenames": [
        "ocean_constants.nc", "ocean_byte_masks.nc", "ocean_basin.nc", "diaptr_basin_masks.nc", "ocean_zostoga.nc"
      ],
      "hybrid_heights_files": [],
      "masked": {
      },
      "halo_options": {
      }
    }
  }
}
